simple_toml_configurator/__init__.py
simple_toml_configurator/exceptions.py
simple_toml_configurator/toml_configurator.py
Simple_TOML_Configurator-1.3.0.dist-info/LICENSE
Simple_TOML_Configurator-1.3.0.dist-info/METADATA
Simple_TOML_Configurator-1.3.0.dist-info/WHEEL
Simple_TOML_Configurator-1.3.0.dist-info/top_level.txt
Simple_TOML_Configurator-1.3.0.dist-info/RECORD
