Metadata-Version: 2.1
Name: Simple-TOML-Configurator
Version: 1.3.0
Summary: A simple TOML configurator for Python
Author-email: GilbN <me@gilbn.dev>
License: MIT License
Project-URL: Homepage, https://github.com/GilbN/Simple-TOML-Configurator
Keywords: configuration,TOML,settings,management,Python
Classifier: License :: OSI Approved :: MIT License
Classifier: Programming Language :: Python
Classifier: Programming Language :: Python :: 3.7
Classifier: Programming Language :: Python :: 3.8
Classifier: Programming Language :: Python :: 3.9
Classifier: Programming Language :: Python :: 3.10
Classifier: Programming Language :: Python :: 3.11
Requires-Python: >=3.7.0
License-File: LICENSE
Requires-Dist: tomlkit >=0.12.1
Requires-Dist: python-dateutil >=2.8.2
Provides-Extra: dev
Requires-Dist: pytest ; extra == 'dev'
Requires-Dist: pytest-cov ; extra == 'dev'
Requires-Dist: pytest-mock ; extra == 'dev'
